MANIFEST.in
setup.py
gitpyport/Fn.dll
gitpyport/__init__.py
gitpyport/engine.py
gitpyport/unzip.exe
gitpyport.egg-info/PKG-INFO
gitpyport.egg-info/SOURCES.txt
gitpyport.egg-info/dependency_links.txt
gitpyport.egg-info/not-zip-safe
gitpyport.egg-info/top_level.txt